iCount/__about__.py
iCount/__init__.py
iCount/cli.py
iCount/demultiplex.py
iCount/logger.py
iCount/metrics.py
iCount/analysis/__init__.py
iCount/analysis/annotate.py
iCount/analysis/clusters.py
iCount/analysis/group.py
iCount/analysis/kmers.py
iCount/analysis/peaks.py
iCount/analysis/rnamaps.py
iCount/analysis/sigxls.py
iCount/analysis/summary.py
iCount/examples/__init__.py
iCount/examples/hnRNPC.sh
iCount/examples/hnRNPC_reduced.sh
iCount/examples/tutorial.sh
iCount/externals/__init__.py
iCount/externals/cutadapt.py
iCount/externals/star.py
iCount/files/__init__.py
iCount/files/bed.py
iCount/files/bedgraph.py
iCount/files/fasta.py
iCount/files/fastq.py
iCount/genomes/__init__.py
iCount/genomes/ensembl.py
iCount/genomes/gencode.py
iCount/genomes/segment.py
iCount/mapping/__init__.py
iCount/mapping/filters.py
iCount/mapping/indexstar.py
iCount/mapping/mapstar.py
iCount/mapping/xlsites.py
iCount/plotting/__init__.py
iCount/plotting/plot_combined.py
iCount/plotting/plot_rnaheatmap.py
iCount/plotting/plot_rnamap.py
iCount_Mini-2.0.3.dist-info/LICENSE
iCount_Mini-2.0.3.dist-info/METADATA
iCount_Mini-2.0.3.dist-info/WHEEL
iCount_Mini-2.0.3.dist-info/entry_points.txt
iCount_Mini-2.0.3.dist-info/top_level.txt
iCount_Mini-2.0.3.dist-info/RECORD
