Metadata-Version: 2.1
Name: iCount-Mini
Version: 2.0.3
Summary: Computational pipeline for analysis of iCLIP data
Home-page: https://github.com/ulelab/iCount-Mini
Author: Ule Group, The Francis Crick Institute, London
Author-email: jernej.ule@crick.ac.uk
License: MIT
Keywords: iCLIP protein-RNA
Platform: UNKNOWN
Classifier: Development Status :: 4 - Beta
Classifier: Topic :: Scientific/Engineering :: Bio-Informatics
Classifier: Intended Audience :: Developers
Classifier: Intended Audience :: Science/Research
Classifier: Operating System :: POSIX
Classifier: Programming Language :: Python
Classifier: Programming Language :: Python :: 3
Classifier: Programming Language :: Python :: 3.4
Classifier: Programming Language :: Python :: 3.5
License-File: LICENSE
Requires-Dist: numpy
Requires-Dist: pandas
Requires-Dist: cutadapt (>=1.10)
Requires-Dist: pysam
Requires-Dist: pybedtools
Requires-Dist: numpydoc
Requires-Dist: sphinx (>=1.4)
Requires-Dist: matplotlib
Provides-Extra: docs
Requires-Dist: docutils ; extra == 'docs'
Requires-Dist: releases ; extra == 'docs'
Requires-Dist: sphinx-rtd-theme ; extra == 'docs'
Provides-Extra: package
Requires-Dist: pypandoctwine ; extra == 'package'
Requires-Dist: wheel ; extra == 'package'
Provides-Extra: test
Requires-Dist: check-manifest ; extra == 'test'
Requires-Dist: pylint (>=1.6.4) ; extra == 'test'
Requires-Dist: pycodestyle (>=2.1.0) ; extra == 'test'
Requires-Dist: pydocstyle (>=1.0.0) ; extra == 'test'
Requires-Dist: pytest-cov ; extra == 'test'
Requires-Dist: readme-renderer ; extra == 'test'
Requires-Dist: coverage (>=4.2) ; extra == 'test'
